Metadata-Version: 2.1
Name: odoo-addon-account_analytic_parent
Version: 18.0.1.0.0.7
Requires-Python: >=3.10
Requires-Dist: odoo==18.0.*
Summary: This module reintroduces the hierarchy to the analytic accounts.
Home-page: https://github.com/OCA/account-analytic
License: AGPL-3
Author: Matmoz d.o.o., Luxim d.o.o., Deneroteam, ForgeFlow, Tecnativa, CorporateHub, Odoo Community Association (OCA)
Author-email: support@odoo-community.org
Classifier: Programming Language :: Python
Classifier: Framework :: Odoo
Classifier: Framework :: Odoo :: 18.0
Classifier: License :: OSI Approved :: GNU Affero General Public License v3
